mm_pos/__init__.py
mm_pos/api.py
mm_pos/core.py
mm_pos/db.py
mm_pos/inventory.py
mm_pos/menu.py
mm_pos/order.py
mm_pos/payment.py
mm_pos/receipt.py
mm_pos/reports.py
mm_pos/tables.py
pos_mm-0.1.2.dist-info/licenses/LICENSE
pos_mm-0.1.2.dist-info/METADATA
pos_mm-0.1.2.dist-info/WHEEL
pos_mm-0.1.2.dist-info/top_level.txt
pos_mm-0.1.2.dist-info/RECORD
