Metadata-Version: 2.4
Name: pos-mm
Version: 0.1.2
Summary: An open-source Point of Sale library for restaurants.
Author-email: Kelvin Lin <kelvin@bu.edu>
License: MIT
Project-URL: Homepage, https://github.com/KelvinLinBU/mm-pos
Project-URL: Repository, https://github.com/KelvinLinBU/mm-pos
Requires-Python: >=3.9
License-File: LICENSE
Requires-Dist: sqlalchemy>=2.0
Requires-Dist: passlib[bcrypt]
Requires-Dist: python-jose[cryptography]
Requires-Dist: python-multipart
Requires-Dist: fastapi
Dynamic: license-file
